cyber/__init__.py
cyber/lib.py
cyber/vm.py
cyber/lib/cyber.h
cyber/lib/libcyber-linux-x64.so
cyber/lib/libcyber-macos-x64.dylib
cyber/lib/libcyber-windows-x64.dll
cyberlang-0.7.1.dist-info/LICENSE
cyberlang-0.7.1.dist-info/METADATA
cyberlang-0.7.1.dist-info/WHEEL
cyberlang-0.7.1.dist-info/top_level.txt
cyberlang-0.7.1.dist-info/RECORD
