Metadata-Version: 2.1
Name: cyberlang
Version: 0.7.1
Summary: A self-contained Cyber intepreter
Author-email: David Kincaid <daelonsuzuka@gmail.com>
License: MIT License
Project-URL: Homepage, https://github.com/DaelonSuzuka/cyber-python
Project-URL: Repository, https://github.com/DaelonSuzuka/cyber-python
Project-URL: Issues, https://github.com/DaelonSuzuka/cyber-python/issues
Classifier: Development Status :: 4 - Beta
Classifier: Intended Audience :: Developers
Classifier: Operating System :: OS Independent
Classifier: License :: OSI Approved :: MIT License
Classifier: Programming Language :: Python :: 3
Classifier: Programming Language :: Python :: 3.9
Classifier: Programming Language :: Python :: 3.10
Classifier: Programming Language :: Python :: 3.11
Classifier: Programming Language :: Python :: 3.12
Classifier: Programming Language :: Python :: 3.13
Requires-Python: >=3.9
License-File: LICENSE
